hyce/Core_class.py
hyce/TESTING_GUIDE.md
hyce/__init__.py
hyce/build_attr_schema_auto.py
hyce/constraint_kernel.py
hyce/dtype_utils.py
hyce/help_cli.py
vector_demension-0.1.2.dist-info/METADATA
vector_demension-0.1.2.dist-info/WHEEL
vector_demension-0.1.2.dist-info/entry_points.txt
vector_demension-0.1.2.dist-info/RECORD
