Metadata-Version: 2.4
Name: vector-demension
Version: 0.1.2
Summary: Constraint checking engine with vectorized NumPy + Numba (no-scale).
License: Proprietary
Keywords: constraints,routing,numba,numpy
Author: Le Thuc
Author-email: Lethuc2602@gmail.com
Requires-Python: >=3.9
Classifier: License :: Other/Proprietary License
Classifier: Programming Language :: Python :: 3
Classifier: Programming Language :: Python :: 3.9
Classifier: Programming Language :: Python :: 3.10
Classifier: Programming Language :: Python :: 3.11
Classifier: Programming Language :: Python :: 3.12
Classifier: Programming Language :: Python :: 3.13
Classifier: Programming Language :: Python :: 3.14
Requires-Dist: numba (>=0.57)
Requires-Dist: numpy (>=1.22)
